CHANGES
LICENSE
MANIFEST.in
README
setup.py
demo/extending.py
demo/statistics.py
textmodel/__init__.py
textmodel/container.py
textmodel/listtools.py
textmodel/modelbase.py
textmodel/properties.py
textmodel/texeltree.py
textmodel/textmodel.py
textmodel/treebase.py
textmodel/viewbase.py
textmodel.egg-info/PKG-INFO
textmodel.egg-info/SOURCES.txt
textmodel.egg-info/dependency_links.txt
textmodel.egg-info/top_level.txt