Metadata-Version: 1.0
Name: textmodel
Version: 0.3.6
Summary: A data type for storing and manipulating rich text data. It aims to be fast and efficient and it is suited even for very long texts.
Home-page: https://pypi.python.org/pypi/textmodel/
Author: C. Ecker
Author-email: textmodelview@gmail.com
License: BSD
Platform: any
